{
  "fields": [
    {
      "datatype": "INTEGER",
      "description": "Record number",
      "id": "RECORDNO",
      "iscustom": "false",
      "label": "Record number",
      "readonly": "true",
      "required": "false"
    },
    {
      "datatype": "TEXT",
      "description": "Structure name",
      "id": "STRUCTURENAME",
      "iscustom": "false",
      "label": "Ownership structure name",
      "readonly": "false",
      "required": "true"
    },
    {
      "datatype": "ENUM",
      "description": "Reporting period effective start date",
      "id": "FROMPERIOD",
      "iscustom": "false",
      "label": "Reporting period effective start date",
      "readonly": "false",
      "required": "true",
      "valid_values": []
    },
    {
      "datatype": "TEXT",
      "description": "Comment",
      "id": "COMMENT",
      "iscustom": "false",
      "label": "Comment",
      "readonly": "false",
      "required": "false"
    },
    {
      "datatype": "TEXT",
      "description": "State",
      "id": "STATE",
      "iscustom": "false",
      "label": "Period state",
      "readonly": "false",
      "required": "false",
      "valid_values": [
        "draft",
        "activated",
        "review"
      ]
    },
    {
      "datatype": "TEXT",
      "description": "Active or inactive",
      "id": "STATUS",
      "iscustom": "false",
      "label": "Status",
      "readonly": "false",
      "required": "false",
      "valid_values": [
        "active",
        "inactive"
      ]
    },
    {
      "datatype": "TIMESTAMP",
      "description": "Timestamp marking last time this was created.",
      "id": "WHENCREATED",
      "iscustom": "false",
      "label": "When created",
      "readonly": "true",
      "required": "false"
    },
    {
      "datatype": "TIMESTAMP",
      "description": "Timestamp marking last time this was changed.",
      "id": "WHENMODIFIED",
      "iscustom": "false",
      "label": "When modified",
      "readonly": "true",
      "required": "false"
    },
    {
      "datatype": "INTEGER",
      "description": "User who created this.",
      "id": "CREATEDBY",
      "iscustom": "false",
      "label": "Created by",
      "readonly": "true",
      "required": "false"
    },
    {
      "datatype": "INTEGER",
      "description": "User who modified this.",
      "id": "MODIFIEDBY",
      "iscustom": "false",
      "label": "Modified by",
      "readonly": "true",
      "required": "false"
    },
    {
      "datatype": "TEXT",
      "description": "A portable, user-independent, deep-link URL for viewing this record",
      "id": "RECORD_URL",
      "iscustom": "false",
      "label": "Record URL",
      "readonly": "true",
      "required": "false"
    }
  ],
  "object_name": "GCOWNERSHIPSTRUCTUREDETAIL",
  "relationships": []
}